pymodaq_plugins_pixelink/__init__.py
pymodaq_plugins_pixelink/utils.py
pymodaq_plugins_pixelink/app/__init__.py
pymodaq_plugins_pixelink/daq_move_plugins/__init__.py
pymodaq_plugins_pixelink/daq_viewer_plugins/__init__.py
pymodaq_plugins_pixelink/daq_viewer_plugins/plugins_0D/__init__.py
pymodaq_plugins_pixelink/daq_viewer_plugins/plugins_1D/__init__.py
pymodaq_plugins_pixelink/daq_viewer_plugins/plugins_2D/__init__.py
pymodaq_plugins_pixelink/daq_viewer_plugins/plugins_2D/daq_2Dviewer_Pixelink.py
pymodaq_plugins_pixelink/daq_viewer_plugins/plugins_2D/daq_2Dviewer_PixelinkWithLECO.py
pymodaq_plugins_pixelink/daq_viewer_plugins/plugins_ND/__init__.py
pymodaq_plugins_pixelink/exporters/__init__.py
pymodaq_plugins_pixelink/extensions/__init__.py
pymodaq_plugins_pixelink/hardware/__init__.py
pymodaq_plugins_pixelink/hardware/pixelink.py
pymodaq_plugins_pixelink/models/__init__.py
pymodaq_plugins_pixelink/resources/__init__.py
pymodaq_plugins_pixelink/resources/config_B700.json
pymodaq_plugins_pixelink/resources/config_template.toml
pymodaq_plugins_pixelink/resources/extended_publisher.py
pymodaq_plugins_pixelink/scanners/__init__.py
pymodaq_plugins_pixelink-0.0.2.dist-info/METADATA
pymodaq_plugins_pixelink-0.0.2.dist-info/WHEEL
pymodaq_plugins_pixelink-0.0.2.dist-info/entry_points.txt
pymodaq_plugins_pixelink-0.0.2.dist-info/licenses/LICENSE
pymodaq_plugins_pixelink-0.0.2.dist-info/RECORD
